delve/__init__.py
delve/logger.py
delve/metrics.py
delve/pca_layers.py
delve/tools.py
delve/torch_utils.py
delve/torchcallback.py
delve/writers.py
delve-0.1.50.dist-info/LICENSE
delve-0.1.50.dist-info/METADATA
delve-0.1.50.dist-info/WHEEL
delve-0.1.50.dist-info/top_level.txt
delve-0.1.50.dist-info/RECORD
