Metadata-Version: 2.1
Name: delve
Version: 0.1.50
Summary: Delve lets you monitor PyTorch model layer saturation during training
Home-page: https://github.com/delve-team/delve
Author: Mats L. Richter & Justin Shenk
Author-email: shenk.justin@gmail.com
License: MIT license
Project-URL: Bug Tracker, https://github.com/delve-team/delve/issues
Project-URL: Documentation, https://delve-docs.readthedocs.io/en/latest/
Project-URL: Source Code, https://github.com/delve-team/delve
Keywords: deep learning,machine learning,pytorch,saturation,pruning,saturation,AI
Classifier: Development Status :: 2 - Pre-Alpha
Classifier: Intended Audience :: Developers
Classifier: License :: OSI Approved :: MIT License
Classifier: Intended Audience :: Education
Classifier: Intended Audience :: Science/Research
Classifier: Programming Language :: Python :: 3.6
Classifier: Programming Language :: Python :: 3.7
Classifier: Programming Language :: Python :: 3.8
Classifier: Programming Language :: Python :: 3.9
Classifier: Programming Language :: Python :: 3.10
Classifier: Topic :: Scientific/Engineering :: Mathematics
Classifier: Topic :: Software Development :: Libraries :: Python Modules
Classifier: Topic :: Software Development :: Libraries
Requires-Python: >=3.6
License-File: LICENSE
Requires-Dist: tensorboardX
Requires-Dist: tqdm
Requires-Dist: matplotlib
Requires-Dist: pandas
Requires-Dist: torch
